philomath/__init__.py
philomath-0.0.0.dist-info/METADATA
philomath-0.0.0.dist-info/WHEEL
philomath-0.0.0.dist-info/RECORD
